README.md
setup.py
mo_parsing/__init__.py
mo_parsing/cache.py
mo_parsing/core.py
mo_parsing/debug.py
mo_parsing/engine.py
mo_parsing/enhancement.py
mo_parsing/exceptions.py
mo_parsing/expressions.py
mo_parsing/helpers.py
mo_parsing/infix.py
mo_parsing/profile.py
mo_parsing/regex.py
mo_parsing/results.py
mo_parsing/tokens.py
mo_parsing/utils.py
moz_sql_parser/__init__.py
moz_sql_parser/debugs.py
moz_sql_parser/formatting.py
moz_sql_parser/keywords.py
moz_sql_parser/sql_parser.py
moz_sql_parser/utils.py
moz_sql_parser/windows.py
moz_sql_parser.egg-info/PKG-INFO
moz_sql_parser.egg-info/SOURCES.txt
moz_sql_parser.egg-info/dependency_links.txt
moz_sql_parser.egg-info/requires.txt
moz_sql_parser.egg-info/top_level.txt
moz_sql_parser.egg-info/zip-safe